dev_tools/__init__.py
dev_tools/create_package.py
develop_tools-1.2.0.dist-info/LICENSE
develop_tools-1.2.0.dist-info/METADATA
develop_tools-1.2.0.dist-info/WHEEL
develop_tools-1.2.0.dist-info/entry_points.txt
develop_tools-1.2.0.dist-info/top_level.txt
develop_tools-1.2.0.dist-info/zip-safe
develop_tools-1.2.0.dist-info/RECORD
