Metadata-Version: 2.1
Name: develop_tools
Version: 1.2.0
Summary: python scripts useful for python development
Home-page: https://github.com/javatechy/dokr
Author: Rupert Hußnätter
Author-email: 
License: Copyright (c) 2024 Rupert Hußnätter
Classifier: Programming Language :: Python :: 3
Classifier: License :: OSI Approved :: MIT License
Classifier: Operating System :: OS Independent
License-File: LICENSE
Requires-Dist: setuptools<=75.6.0
